Workbook

Sheet Summary
A1: Parental Leave Dataset — Overall Summary
A3: Total companies analyzed | B3: =COUNTA('Source Data'!$A$2:$A$1602) -> 1601
A4: Number of industries represented | B4: 186
A6: Leave Type | B6: Average (weeks) | C6: Min (weeks) | D6: Max (weeks) | E6: Companies Reporting
A7: Paid Maternity Leave | B7: =AVERAGE('Source Data'!$C$2:$C$1602) -> 10.909119 | C7: =MIN('Source Data'!$C$2:$C$1602) -> 0 | D7: =MAX('Source Data'!$C$2:$C$1602) -> 52 | E7: =COUNT('Source Data'!$C$2:$C$1602) -> 1601
A8: Unpaid Maternity Leave | B8: =AVERAGE('Source Data'!$D$2:$D$1602) -> 6.6288487 | C8: =MIN('Source Data'!$D$2:$D$1602) -> 0 | D8: =MAX('Source Data'!$D$2:$D$1602) -> 52 | E8: =COUNT('Source Data'!$D$2:$D$1602) -> 1494
A9: Paid Paternity Leave | B9: =AVERAGE('Source Data'!$E$2:$E$1602) -> 7.3321799 | C9: =MIN('Source Data'!$E$2:$E$1602) -> 0 | D9: =MAX('Source Data'!$E$2:$E$1602) -> 51 | E9: =COUNT('Source Data'!$E$2:$E$1602) -> 289
A10: Unpaid Paternity Leave | B10: =AVERAGE('Source Data'!$F$2:$F$1602) -> 7.734375 | C10: =MIN('Source Data'!$F$2:$F$1602) -> 0 | D10: =MAX('Source Data'!$F$2:$F$1602) -> 29 | E10: =COUNT('Source Data'!$F$2:$F$1602) -> 64
A12: Assumptions & Notes:
A13: - Leave figures are expressed in weeks.
A14: - Averages/Min/Max are computed only over companies that reported that leave type; blank cells are ignored by AVERAGE/MIN/MAX/COUNT.
A15: - 3 companies (ASML, INK Communications Co., Rokt) had a blank Industry and are grouped as 'Unknown' in the Industry Summary sheet.
A16: - In the Leave Gap Analysis sheet, a blank paid-leave value is treated as 0 weeks so a gap can be computed for every company.
A17: - Source: parental_leave.csv, 1601 company rows (originally read as Latin-1 encoded CSV with trailing empty columns removed).

Sheet Source Data
A1: Company | B1: Industry | C1: Paid Maternity Leave | D1: Unpaid Maternity Leave | E1: Paid Paternity Leave | F1: Unpaid Paternity Leave
A2: Epsilon | B2: Advertising | C2: 6 | D2: 6 | E2: 6 | F2: 6
A3: The Walt Disney Company | B3: Arts & Entertainment | C3: 5 | D3: 4 | E3: 4.5 | F3: 4
A4: Guild Education | B4: Business Services: Other | C4: 14 | D4: 0 | E4: 8 | F4: 4
A5: WeWork | B5: Business Services: Other | C5: 14 | D5: 2 | E5: 16 | F5: 4
A6: Randstad USA | B6: Business Services: Staffing & Outsourcing | C6: 5 | D6: 7 | E6: 0 | F6: 0
A7: Bain & Company | B7: Consulting Services | C7: 20.5 | D7: 5 | E7: 21 | F7: 5
A8: World 50 | B8: Consulting Services | C8: 8 | D8: 12 | E8: 1 | F8: 12
A9: ConAgra Foods, Inc. | B9: Consumer Packaged Goods: Packaged Foods | C9: 6 | D9: 6 | E9: 2 | F9: 6
A10: Anduril Industries | B10: Defense & Space | C10: 16 | D10: 0 | E10: 16 | F10: 0
A11: Northrop Grumman | B11: Defense & Space | C11: 3 | D11: 12 | E11: 2 | F11: 12
A12: The University of Vermont | B12: Educational Services: College & Universities | C12: 0 | D12: 12 | E12: 0 | F12: 12
A13: Belden | B13: Electronics: Manufacturing | C13: 0 | D13: 12 | E13: 0 | F13: 12
... A45: T-Mobile | B45: Telecommunications | C45: 7.5 | D45: 3 | E45: 3 | F45: 4
A46: CBIZ | B46: Accounting Services | C46: 3.5 | D46: 6 | E46: 1
A47: CliftonLarsonAllen | B47: Accounting Services | C47: 9.5 | D47: 6 | E47: 6
A48: Forvis | B48: Accounting Services | C48: 12 | E48: 2 | F48: 12
A49: Grant Thornton | B49: Accounting Services | C49: 51 | D49: 51 | E49: 51
A50: RSM US | B50: Accounting Services | C50: 12 | D50: 0 | E50: 7
A51: LiveRamp | B51: Advertising | C51: 16 | D51: 6 | E51: 16
A52: Boeing | B52: Aerospace | C52: 12 | D52: 9 | E52: 12
A53: Cessna Aircraft Company | B53: Aerospace | C53: 8 | D53: 10 | E53: 12
A54: Collins Aerospace | B54: Aerospace | C54: 12 | D54: 0 | E54: 4
A55: Collins Aerospace | B55: Aerospace | C55: 4 | D55: 12 | E55: 4
A56: Lockheed Martin Corporation | B56: Aerospace | C56: 6 | D56: 1 | E56: 4
A57: FCA US LLC | B57: Automotive: Manufacturers | C57: 7.5 | D57: 1 | E57: 6
A58: Ford Motor Company | B58: Automotive: Manufacturers | C58: 12 | D58: 0 | E58: 8
A59: General Motors | B59: Automotive: Manufacturers | C59: 12 | D59: 12 | E59: 12
A60: Toyota North America | B60: Automotive: Manufacturers | C60: 6 | D60: 1.5 | E60: 0
... A77: Slalom | B77: Consulting Services | C77: 14 | D77: 0 | E77: 4
A78: Campari America | B78: Consumer Packaged Goods: Beverages | C78: 12 | E78: 12 | F78: 6
A79: Miller Coors | B79: Consumer Packaged Goods: Beverages | C79: 16 | D79: 34 | E79: 16
A80: General Mills | B80: Consumer Packaged Goods: Packaged Foods | C80: 18 | D80: 12 | E80: 12
A81: Mondelez International, Inc. | B81: Consumer Packaged Goods: Packaged Foods | C81: 6 | D81: 9.5 | E81: 6
A82: Johnson & Johnson | B82: Consumer Packaged Goods: Packaged Products | C82: 16 | D82: 24 | E82: 8
A83: Reckitt Benckiser | B83: Consumer Packaged Goods: Packaged Products | C83: 21 | D83: 31 | E83: 16
A84: Unilever | B84: Consumer Packaged Goods: Packaged Products | C84: 16 | D84: 4 | E84: 8
A85: Hasbro Inc. | B85: Consumer Packaged Goods: Toys & Baby Products | C85: 18 | D85: 18 | F85: 13
A86: L'Oral USA | B86: Cosmetics | C86: 12 | D86: 0 | E86: 8
A87: Raytheon Technologies | B87: Defense & Space | C87: 7.5 | D87: 3 | E87: 3
A88: Rice University | B88: Educational Services: College & Universities | C88: 6 | D88: 6 | E88: 0
A89: University of Minnesota | B89: Educational Services: College & Universities | C89: 6 | D89: 6 | E89: 6
A90: Walden University | B90: Educational Services: College & Universities | C90: 6 | D90: 6 | E90: 1
A91: Cengage Learning | B91: Educational Services: E-Learning | C91: 12 | D91: 0 | E91: 12
A92: Samsung Electronics | B92: Electronics: Manufacturing | C92: 2 | D92: 12 | E92: 2
A93: Apollo Global Management | B93: Finance: Asset Management | C93: 16 | E93: 2 | F93: 0
A94: Capital Group | B94: Finance: Asset Management | C94: 12 | D94: 0 | E94: 18
A95: Merrill | B95: Finance: Asset Management | C95: 11 | D95: 6 | E95: 16
A96: Discover Financial Services | B96: Finance: Credit & Fund Services | C96: 16 | D96: 0 | E96: 2
A97: Mastercard | B97: Finance: Credit & Fund Services | C97: 16 | D97: 0 | E97: 16
A98: Ally Financial | B98: Finance: Diversified | C98: 12 | D98: 0 | E98: 12
A99: Ameriprise Financial | B99: Finance: Diversified | C99: 12 | D99: 4 | E99: 2
A100: Charles Schwab | B100: Finance: Diversified | C100: 8 | D100: 6 | E100: 6
A101: Citigroup | B101: Finance: Diversified | C101: 16 | D101: 4 | E101: 4.5
A102: Deutsche Bank | B102: Finance: Diversified | C102: 16 | D102: 5 | E102: 16
A103: DTCC | B103: Finance: Diversified | C103: 16 | D103: 4 | E103: 16
A104: Goldman Sachs | B104: Finance: Diversified | C104: 20 | D104: 3 | E104: 20
A105: Macquarie Group | B105: Finance: Diversified | C105: 16 | D105: 0 | E105: 6
... A122: Fresenius | B122: Healthcare: Diversified | C122: 4 | D122: 12 | E122: 0
A123: Aurora Health Care | B123: Healthcare: Hospitals & Clinics | C123: 0 | D123: 12 | F123: 0
A124: Mayo Clinic | B124: Healthcare: Hospitals & Clinics | C124: 5 | D124: 6.5 | E124: 0
A125: Universal Health Services, Inc. | B125: Healthcare: Hospitals & Clinics | C125: 0 | D125: 12 | E125: 0
A126: University of Pittsburgh Medical Center | B126: Healthcare: Hospitals & Clinics | C126: 2 | D126: 6 | E126: 2
A127: Quest Diagnostics | B127: Healthcare: Laboratory Testing | C127: 6 | D127: 0 | F127: 0
A128: Becton, Dickinson and Company | B128: Healthcare: Medical Devices | C128: 6 | D128: 12 | E128: 6
A129: Medtronic | B129: Healthcare: Medical Devices | C129: 12 | D129: 2 | E129: 0
A130: Zimmer Biomet | B130: Healthcare: Medical Devices | C130: 8 | D130: 4 | E130: 6
A131: Flatiron Health | B131: Healthcare: Telemedicine | C131: 30 | D131: 15 | E131: 30
A132: Choice Hotels | B132: Hospitality: Hotels | C132: 12 | D132: 0 | E132: 4
A133: Marriott International | B133: Hospitality: Hotels | C133: 8 | D133: 8 | E133: 8
A134: McDonald's | B134: Hospitality: Restaurants | C134: 12 | D134: 12 | F134: 29
A135: Starbucks | B135: Hospitality: Restaurants | C135: 6 | D135: 9 | E135: 6
A136: Perkins + Will | B136: Industrial: Architecture & Design | C136: 4 | D136: 0 | E136: 4
A137: Owens Corning | B137: Industrial: Building Materials Manufacturing | C137: 4 | D137: 4 | F137: 2
A138: Power Home Remodeling | B138: Industrial: Construction Company | C138: 12 | D138: 0 | E138: 3
A139: 3M | B139: Industrial: Diversified | C139: 10 | D139: 10 | F139: 10
A140: Parker Hannifin | B140: Industrial: Diversified | C140: 4 | D140: 8 | E140: 0
A141: BEUMER Group | B141: Industrial: Equipment Manufacturing | C141: 4 | D141: 0 | E141: 4
A142: Caterpillar | B142: Industrial: Equipment Manufacturing | C142: 5 | D142: 6 | E142: 4
A143: CNH Industrial America | B143: Industrial: Equipment Manufacturing | C143: 6 | D143: 6 | E143: 4
A144: Cummins | B144: Industrial: Equipment Manufacturing | C144: 12 | D144: 10 | E144: 6
A145: Hilti Corporation | B145: Industrial: Equipment Manufacturing | C145: 12 | D145: 2 | E145: 4
A146: nVent | B146: Industrial: Equipment Manufacturing | C146: 6 | D146: 0 | E146: 6
A147: Rockwell Automation | B147: Industrial: Equipment Manufacturing | C147: 6 | D147: 9 | E147: 6
A148: McMaster-Carr | B148: Industrial: Other | C148: 16 | D148: 4 | E148: 4
A149: Argus Media | B149: Information Services: Diversified | C149: 8 | D149: 12 | E149: 1
A150: LAC-Group | B150: Information Services: Diversified | C150: 32.5 | D150: 0 | E150: 35
A151: S&P Global | B151: Information Services: Financial | C151: 18 | D151: 0 | E151: 23
... A156: Aetna | B156: Insurance: Health | C156: 12 | D156: 12 | E156: 4
A157: Health Care Service Corporation | B157: Insurance: Health | C157: 6 | D157: 3 | F157: 6
A158: Highmark Inc. | B158: Insurance: Health | C158: 6 | D158: 4 | F158: 4
A159: Humana | B159: Insurance: Health | C159: 6 | D159: 6 | E159: 6
A160: Kaiser Permanente | B160: Insurance: Health | C160: 3 | D160: 3 | E160: 0
A161: Combined Insurance | B161: Insurance: Life | C161: 15 | D161: 3 | F161: 0
A162: Root Insurance | B162: Insurance: Property & Casualty | C162: 12 | D162: 0 | E162: 12
A163: State Farm | B163: Insurance: Property & Casualty | C163: 9 | D163: 0 | E163: 6
A164: The Hanover Insurance Group | B164: Insurance: Property & Casualty | C164: 8 | D164: 4 | E164: 2
A165: Holland & Knight LLP | B165: Law Firm | C165: 4 | D165: 8 | E165: 6
A166: Orrick, Herrington & Sutcliffe LLP | B166: Law Firm | C166: 23 | D166: 2 | E166: 16
A167: Expedia Group | B167: Leisure, Travel & Tourism | C167: 18 | D167: 4 | E167: 12
...

Sheet Industry Summary
A1: Industry Summary — Average / Min / Max Leave by Industry (weeks)
A2: All figures pull live from the 'Source Data' sheet via AVERAGEIF / MINIFS / MAXIFS. Blank source cells are ignored automatically.
A4: Industry | B4: Company Count | C4: Paid Maternity Leave — Avg | D4: Paid Maternity Leave — Min | E4: Paid Maternity Leave — Max | F4: Unpaid Maternity Leave — Avg | G4: Unpaid Maternity Leave — Min | H4: Unpaid Maternity Leave — Max | I4: Paid Paternity Leave — Avg | J4: Paid Paternity Leave — Min | K4: Paid Paternity Leave — Max | L4: Unpaid Paternity Leave — Avg | M4: Unpaid Paternity Leave — Min | N4: Unpaid Paternity Leave — Max
A5: Accounting Services | B5: =COUNTIF('Source Data'!$B$2:$B$1602,$A5) -> 13 | C5: =IF(COUNTIFS('Source Data'!$B$2:$B$1602,$A5,'Source Data'!$C$2:$C$1602,"<>")=0,"",AVERAGEIF('Source Data'!$B$2:$B$1602,$A5,'Source Data'!$C$2:$C$1602)) -> 11.846154 | D5: =IF(COUNTIFS('Source Data'!$B$2:$B$1602,$A5,'Source Data'!$C$2:$C$1602,"<>")=0,"",_xlfn.MINIFS('Source Data'!$C$2:$C$1602,'Source Data'!$B$2:$B$1602,$A5)) -> 3.5 | E5: =IF(COUNTIFS('Source Data'!$B$2:$B$1602,$A5,'Source Data'!$C$2:$C$1602,"<>")=0,"",_xlfn.MAXIFS('Source Data'!$C$2:$C$1602,'Source Data'!$B$2:$B$1602,$A5)) -> 51 | F5: =IF(COUNTIFS('Source Data'!$B$2:$B$1602,$A5,'Source Data'!$D$2:$D$1602,"<>")=0,"",AVERAGEIF('Source Data'!$B$2:$B$1602,$A5,'Source Data'!$D$2:$D$1602)) -> 12.25 | G5: =IF(COUNTIFS('Source Data'!$B$2:$B$1602,$A5,'Source Data'!$D$2:$D$1602,"<>")=0,"",_xlfn.MINIFS('Source Data'!$D$2:$D$1602,'Source Data'!$B$2:$B$1602,$A5)) -> 0 | H5: =IF(COUNTIFS('Source Data'!$B$2:$B$1602,$A5,'Source Data'!$D$2:$D$1602,"<>")=0,"",_xlfn.MAXIFS('Source Data'!$D$2:$D$1602,'Source Data'!$B$2:$B$1602,$A5)) -> 52 | I5: =IF(COUNTIFS('Source Data'!$B$2:$B$1602,$A5,'Source Data'!$E$2:$E$1602,"<>")=0,"",AVERAGEIF('Source Data'!$B$2:$B$1602,$A5,'Source Data'!$E$2:$E$1602)) -> 13.4 | J5: =IF(COUNTIFS('Source Data'!$B$2:$B$1602,$A5,'Source Data'!$E$2:$E$1602,"<>")=0,"",_xlfn.MINIFS('Source Data'!$E$2:$E$1602,'Source Data'!$B$2:$B$1602,$A5)) -> 1 | K5: =IF(COUNTIFS('Source Data'!$B$2:$B$1602,$A5,'Source Data'!$E$2:$E$1602,"<>")=0,"",_xlfn.MAXIFS('Source Data'!$E$2:$E$1602,'Source Data'!$B$2:$B$1602,$A5)) -> 51 | L5: =IF(COUNTIFS('Source Data'!$B$2:$B$1602,$A5,'Source Data'!$F$2:$F$1602,"<>")=0,"",AVERAGEIF('Source Data'!$B$2:$B$1602,$A5,'Source Data'!$F$2:$F$1602)) -> 12 | M5: =IF(COUNTIFS('Source Data'!$B$2:$B$1602,$A5,'Source Data'!$F$2:$F$1602,"<>")=0,"",_xlfn.MINIFS('Source Data'!$F$2:$F$1602,'Source Data'!$B$2:$B$1602,$A5)) -> 12 | N5: =IF(COUNTIFS('Source Data'!$B$2:$B$1602,$A5,'Source Data'!$F$2:$F$1602,"<>")=0,"",_xlfn.MAXIFS('Source Data'!$F$2:$F$1602,'Source Data'!$B$2:$B$1602,$A5)) -> 12
A6: Advertising | B6: =COUNTIF('Source Data'!$B$2:$B$1602,$A6) -> 50 | C6: =IF(COUNTIFS('Source Data'!$B$2:$B$1602,$A6,'Source Data'!$C$2:$C$1602,"<>")=0,"",AVERAGEIF('Source Data'!$B$2:$B$1602,$A6,'Source Data'!$C$2:$C$1602)) -> 9.41 | D6: =IF(COUNTIFS('Source Data'!$B$2:$B$1602,$A6,'Source Data'!$C$2:$C$1602,"<>")=0,"",_xlfn.MINIFS('Source Data'!$C$2:$C$1602,'Source Data'!$B$2:$B$1602,$A6)) -> 1 | E6: =IF(COUNTIFS('Source Data'!$B$2:$B$1602,$A6,'Source Data'!$C$2:$C$1602,"<>")=0,"",_xlfn.MAXIFS('Source Data'!$C$2:$C$1602,'Source Data'!$B$2:$B$1602,$A6)) -> 48 | F6: =IF(COUNTIFS('Source Data'!$B$2:$B$1602,$A6,'Source Data'!$D$2:$D$1602,"<>")=0,"",AVERAGEIF('Source Data'!$B$2:$B$1602,$A6,'Source Data'!$D$2:$D$1602)) -> 5.4893617 | G6: =IF(COUNTIFS('Source Data'!$B$2:$B$1602,$A6,'Source Data'!$D$2:$D$1602,"<>")=0,"",_xlfn.MINIFS('Source Data'!$D$2:$D$1602,'Source Data'!$B$2:$B$1602,$A6)) -> 0 | H6: =IF(COUNTIFS('Source Data'!$B$2:$B$1602,$A6,'Source Data'!$D$2:$D$1602,"<>")=0,"",_xlfn.MAXIFS('Source Data'!$D$2:$D$1602,'Source Data'!$B$2:$B$1602,$A6)) -> 36 | I6: =IF(COUNTIFS('Source Data'!$B$2:$B$1602,$A6,'Source Data'!$E$2:$E$1602,"<>")=0,"",AVERAGEIF('Source Data'!$B$2:$B$1602,$A6,'Source Data'!$E$2:$E$1602)) -> 11 | J6: =IF(COUNTIFS('Source Data'!$B$2:$B$1602,$A6,'Source Data'!$E$2:$E$1602,"<>")=0,"",_xlfn.MINIFS('Source Data'!$E$2:$E$1602,'Source Data'!$B$2:$B$1602,$A6)) -> 6 | K6: =IF(COUNTIFS('Source Data'!$B$2:$B$1602,$A6,'Source Data'!$E$2:$E$1602,"<>")=0,"",_xlfn.MAXIFS('Source Data'!$E$2:$E$1602,'Source Data'!$B$2:$B$1602,$A6)) -> 16 | L6: =IF(COUNTIFS('Source Data'!$B$2:$B$1602,$A6,'Source Data'!$F$2:$F$1602,"<>")=0,"",AVERAGEIF('Source Data'!$B$2:$B$1602,$A6,'Source Data'!$F$2:$F$1602)) -> 6 | M6: =IF(COUNTIFS('Source Data'!$B$2:$B$1602,$A6,'Source Data'!$F$2:$F$1602,"<>")=0,"",_xlfn.MINIFS('Source Data'!$F$2:$F$1602,'Source Data'!$B$2:$B$1602,$A6)) -> 6 | N6: =IF(COUNTIFS('Source Data'!$B$2:$B$1602,$A6,'Source Data'!$F$2:$F$1602,"<>")=0,"",_xlfn.MAXIFS('Source Data'!$F$2:$F$1602,'Source Data'!$B$2:$B$1602,$A6)) -> 6
A7: Advertising: Market Research | B7: =COUNTIF('Source Data'!$B$2:$B$1602,$A7) -> 3 | C7: =IF(COUNTIFS('Source Data'!$B$2:$B$1602,$A7,'Source Data'!$C$2:$C$1602,"<>")=0,"",AVERAGEIF('Source Data'!$B$2:$B$1602,$A7,'Source Data'!$C$2:$C$1602)) -> 9.3333333 | D7: =IF(COUNTIFS('Source Data'!$B$2:$B$1602,$A7,'Source Data'!$C$2:$C$1602,"<>")=0,"",_xlfn.MINIFS('Source Data'!$C$2:$C$1602,'Source Data'!$B$2:$B$1602,$A7)) -> 4 | E7: =IF(COUNTIFS('Source Data'!$B$2:$B$1602,$A7,'Source Data'!$C$2:$C$1602,"<>")=0,"",_xlfn.MAXIFS('Source Data'!$C$2:$C$1602,'Source Data'!$B$2:$B$1602,$A7)) -> 12 | F7: =IF(COUNTIFS('Source Data'!$B$2:$B$1602,$A7,'Source Data'!$D$2:$D$1602,"<>")=0,"",AVERAGEIF('Source Data'!$B$2:$B$1602,$A7,'Source Data'!$D$2:$D$1602)) -> 6 | G7: =IF(COUNTIFS('Source Data'!$B$2:$B$1602,$A7,'Source Data'!$D$2:$D$1602,"<>")=0,"",_xlfn.MINIFS('Source Data'!$D$2:$D$1602,'Source Data'!$B$2:$B$1602,$A7)) -> 0 | H7: =IF(COUNTIFS('Source Data'!$B$2:$B$1602,$A7,'Source Data'!$D$2:$D$1602,"<>")=0,"",_xlfn.MAXIFS('Source Data'!$D$2:$D$1602,'Source Data'!$B$2:$B$1602,$A7)) -> 12 | I7: =IF(COUNTIFS('Source Data'!$B$2:$B$1602,$A7,'Source Data'!$E$2:$E$1602,"<>")=0,"",AVERAGEIF('Source Data'!$B$2:$B$1602,$A7,'Source Data'!$E$2:$E$1602)) | J7: =IF(COUNTIFS('Source Data'!$B$2:$B$1602,$A7,'Source Data'!$E$2:$E$1602,"<>")=0,"",_xlfn.MINIFS('Source Data'!$E$2:$E$1602,'Source Data'!$B$2:$B$1602,$A7)) | K7: =IF(COUNTIFS('Source Data'!$B$2:$B$1602,$A7,'Source Data'!$E$2:$E$1602,"<>")=0,"",_xlfn.MAXIFS('Source Data'!$E$2:$E$1602,'Source Data'!$B$2:$B$1602,$A7)) | L7: =IF(COUNTIFS('Source Data'!$B$2:$B$1602,$A7,'Source Data'!$F$2:$F$1602,"<>")=0,"",AVERAGEIF('Source Data'!$B$2:$B$1602,$A7,'Source Data'!$F$2:$F$1602)) | M7: =IF(COUNTIFS('Source Data'!$B$2:$B$1602,$A7,'Source Data'!$F$2:$F$1602,"<>")=0,"",_xlfn.MINIFS('Source Data'!$F$2:$F$1602,'Source Data'!$B$2:$B$1602,$A7)) | N7: =IF(COUNTIFS('Source Data'!$B$2:$B$1602,$A7,'Source Data'!$F$2:$F$1602,"<>")=0,"",_xlfn.MAXIFS('Source Data'!$F$2:$F$1602,'Source Data'!$B$2:$B$1602,$A7))
A8: Aerospace | B8: =COUNTIF('Source Data'!$B$2:$B$1602,$A8) -> 9 | C8: =IF(COUNTIFS('Source Data'!$B$2:$B$1602,$A8,'Source Data'!$C$2:$C$1602,"<>")=0,"",AVERAGEIF('Source Data'!$B$2:$B$1602,$A8,'Source Data'!$C$2:$C$1602)) -> 10 | D8: =IF(COUNTIFS('Source Data'!$B$2:$B$1602,$A8,'Source Data'!$C$2:$C$1602,"<>")=0,"",_xlfn.MINIFS('Source Data'!$C$2:$C$1602,'Source Data'!$B$2:$B$1602,$A8)) -> 4 | E8: =IF(COUNTIFS('Source Data'!$B$2:$B$1602,$A8,'Source Data'!$C$2:$C$1602,"<>")=0,"",_xlfn.MAXIFS('Source Data'!$C$2:$C$1602,'Source Data'!$B$2:$B$1602,$A8)) -> 16 | F8: =IF(COUNTIFS('Source Data'!$B$2:$B$1602,$A8,'Source Data'!$D$2:$D$1602,"<>")=0,"",AVERAGEIF('Source Data'!$B$2:$B$1602,$A8,'Source Data'!$D$2:$D$1602)) -> 6.1111111 | G8: =IF(COUNTIFS('Source Data'!$B$2:$B$1602,$A8,'Source Data'!$D$2:$D$1602,"<>")=0,"",_xlfn.MINIFS('Source Data'!$D$2:$D$1602,'Source Data'!$B$2:$B$1602,$A8)) -> 0 | H8: =IF(COUNTIFS('Source Data'!$B$2:$B$1602,$A8,'Source Data'!$D$2:$D$1602,"<>")=0,"",_xlfn.MAXIFS('Source Data'!$D$2:$D$1602,'Source Data'!$B$2:$B$1602,$A8)) -> 12 | I8: =IF(COUNTIFS('Source Data'!$B$2:$B$1602,$A8,'Source Data'!$E$2:$E$1602,"<>")=0,"",AVERAGEIF('Source Data'!$B$2:$B$1602,$A8,'Source Data'!$E$2:$E$1602)) -> 7.2 | J8: =IF(COUNTIFS('Source Data'!$B$2:$B$1602,$A8,'Source Data'!$E$2:$E$1602,"<>")=0,"",_xlfn.MINIFS('Source Data'!$E$2:$E$1602,'Source Data'!$B$2:$B$1602,$A8)) -> 4 | K8: =IF(COUNTIFS('Source Data'!$B$2:$B$1602,$A8,'Source Data'!$E$2:$E$1602,"<>")=0,"",_xlfn.MAXIFS('Source Data'!$E$2:$E$1602,'Source Data'!$B$2:$B$1602,$A8)) -> 12 | L8: =IF(COUNTIFS('Source Data'!$B$2:$B$1602,$A8,'Source Data'!$F$2:$F$1602,"<>")=0,"",AVERAGEIF('Source Data'!$B$2:$B$1602,$A8,'Source Data'!$F$2:$F$1602)) | M8: =IF(COUNTIFS('Source Data'!$B$2:$B$1602,$A8,'Source Data'!$F$2:$F$1602,"<>")=0,"",_xlfn.MINIFS('Source Data'!$F$2:$F$1602,'Source Data'!$B$2:$B$1602,$A8)) | N8: =IF(COUNTIFS('Source Data'!$B$2:$B$1602,$A8,'Source Data'!$F$2:$F$1602,"<>")=0,"",_xlfn.MAXIFS('Source Data'!$F$2:$F$1602,'Source Data'!$B$2:$B$1602,$A8))
A9: Arts & Entertainment | B9: =COUNTIF('Source Data'!$B$2:$B$1602,$A9) -> 7 | C9: =IF(COUNTIFS('Source Data'!$B$2:$B$1602,$A9,'Source Data'!$C$2:$C$1602,"<>")=0,"",AVERAGEIF('Source Data'!$B$2:$B$1602,$A9,'Source Data'!$C$2:$C$1602)) -> 10.142857 | D9: =IF(COUNTIFS('Source Data'!$B$2:$B$1602,$A9,'Source Data'!$C$2:$C$1602,"<>")=0,"",_xlfn.MINIFS('Source Data'!$C$2:$C$1602,'Source Data'!$B$2:$B$1602,$A9)) -> 0 | E9: =IF(COUNTIFS('Source Data'!$B$2:$B$1602,$A9,'Source Data'!$C$2:$C$1602,"<>")=0,"",_xlfn.MAXIFS('Source Data'!$C$2:$C$1602,'Source Data'!$B$2:$B$1602,$A9)) -> 24 | F9: =IF(COUNTIFS('Source Data'!$B$2:$B$1602,$A9,'Source Data'!$D$2:$D$1602,"<>")=0,"",AVERAGEIF('Source Data'!$B$2:$B$1602,$A9,'Source Data'!$D$2:$D$1602)) -> 7.6 | G9: =IF(COUNTIFS('Source Data'!$B$2:$B$1602,$A9,'Source Data'!$D$2:$D$1602,"<>")=0,"",_xlfn.MINIFS('Source Data'!$D$2:$D$1602,'Source Data'!$B$2:$B$1602,$A9)) -> 0 | H9: =IF(COUNTIFS('Source Data'!$B$2:$B$1602,$A9,'Source Data'!$D$2:$D$1602,"<>")=0,"",_xlfn.MAXIFS('Source Data'!$D$2:$D$1602,'Source Data'!$B$2:$B$1602,$A9)) -> 12 | I9: =IF(COUNTIFS('Source Data'!$B$2:$B$1602,$A9,'Source Data'!$E$2:$E$1602,"<>")=0,"",AVERAGEIF('Source Data'!$B$2:$B$1602,$A9,'Source Data'!$E$2:$E$1602)) -> 5.5 | J9: =IF(COUNTIFS('Source Data'!$B$2:$B$1602,$A9,'Source Data'!$E$2:$E$1602,"<>")=0,"",_xlfn.MINIFS('Source Data'!$E$2:$E$1602,'Source Data'!$B$2:$B$1602,$A9)) -> 0 | K9: =IF(COUNTIFS('Source Data'!$B$2:$B$1602,$A9,'Source Data'!$E$2:$E$1602,"<>")=0,"",_xlfn.MAXIFS('Source Data'!$E$2:$E$1602,'Source Data'!$B$2:$B$1602,$A9)) -> 12 | L9: =IF(COUNTIFS('Source Data'!$B$2:$B$1602,$A9,'Source Data'!$F$2:$F$1602,"<>")=0,"",AVERAGEIF('Source Data'!$B$2:$B$1602,$A9,'Source Data'!$F$2:$F$1602)) -> 4 | M9: =IF(COUNTIFS('Source Data'!$B$2:$B$1602,$A9,'Source Data'!$F$2:$F$1602,"<>")=0,"",_xlfn.MINIFS('Source Data'!$F$2:$F$1602,'Source Data'!$B$2:$B$1602,$A9)) -> 4 | N9: =IF(COUNTIFS('Source Data'!$B$2:$B$1602,$A9,'Source Data'!$F$2:$F$1602,"<>")=0,"",_xlfn.MAXIFS('Source Data'!$F$2:$F$1602,'Source Data'!$B$2:$B$1602,$A9)) -> 4
A10: Automotive: Dealers | B10: =COUNTIF('Source Data'!$B$2:$B$1602,$A10) -> 2 | C10: =IF(COUNTIFS('Source Data'!$B$2:$B$1602,$A10,'Source Data'!$C$2:$C$1602,"<>")=0,"",AVERAGEIF('Source Data'!$B$2:$B$1602,$A10,'Source Data'!$C$2:$C$1602)) -> 5.5 | D10: =IF(COUNTIFS('Source Data'!$B$2:$B$1602,$A10,'Source Data'!$C$2:$C$1602,"<>")=0,"",_xlfn.MINIFS('Source Data'!$C$2:$C$1602,'Source Data'!$B$2:$B$1602,$A10)) -> 3 | E10: =IF(COUNTIFS('Source Data'!$B$2:$B$1602,$A10,'Source Data'!$C$2:$C$1602,"<>")=0,"",_xlfn.MAXIFS('Source Data'!$C$2:$C$1602,'Source Data'!$B$2:$B$1602,$A10)) -> 8 | F10: =IF(COUNTIFS('Source Data'!$B$2:$B$1602,$A10,'Source Data'!$D$2:$D$1602,"<>")=0,"",AVERAGEIF('Source Data'!$B$2:$B$1602,$A10,'Source Data'!$D$2:$D$1602)) -> 6 | G10: =IF(COUNTIFS('Source Data'!$B$2:$B$1602,$A10,'Source Data'!$D$2:$D$1602,"<>")=0,"",_xlfn.MINIFS('Source Data'!$D$2:$D$1602,'Source Data'!$B$2:$B$1602,$A10)) -> 0 | H10: =IF(COUNTIFS('Source Data'!$B$2:$B$1602,$A10,'Source Data'!$D$2:$D$1602,"<>")=0,"",_xlfn.MAXIFS('Source Data'!$D$2:$D$1602,'Source Data'!$B$2:$B$1602,$A10)) -> 12 | I10: =IF(COUNTIFS('Source Data'!$B$2:$B$1602,$A10,'Source Data'!$E$2:$E$1602,"<>")=0,"",AVERAGEIF('Source Data'!$B$2:$B$1602,$A10,'Source Data'!$E$2:$E$1602)) | J10: =IF(COUNTIFS('Source Data'!$B$2:$B$1602,$A10,'Source Data'!$E$2:$E$1602,"<>")=0,"",_xlfn.MINIFS('Source Data'!$E$2:$E$1602,'Source Data'!$B$2:$B$1602,$A10)) | K10: =IF(COUNTIFS('Source Data'!$B$2:$B$1602,$A10,'Source Data'!$E$2:$E$1602,"<>")=0,"",_xlfn.MAXIFS('Source Data'!$E$2:$E$1602,'Source Data'!$B$2:$B$1602,$A10)) | L10: =IF(COUNTIFS('Source Data'!$B$2:$B$1602,$A10,'Source Data'!$F$2:$F$1602,"<>")=0,"",AVERAGEIF('Source Data'!$B$2:$B$1602,$A10,'Source Data'!$F$2:$F$1602)) | M10: =IF(COUNTIFS('Source Data'!$B$2:$B$1602,$A10,'Source Data'!$F$2:$F$1602,"<>")=0,"",_xlfn.MINIFS('Source Data'!$F$2:$F$1602,'Source Data'!$B$2:$B$1602,$A10)) | N10: =IF(COUNTIFS('Source Data'!$B$2:$B$1602,$A10,'Source Data'!$F$2:$F$1602,"<>")=0,"",_xlfn.MAXIFS('Source Data'!$F$2:$F$1602,'Source Data'!$B$2:$B$1602,$A10))
A11: Automotive: Manufacturers | B11: =COUNTIF('Source Data'!$B$2:$B$1602,$A11) -> 6 | C11: =IF(COUNTIFS('Source Data'!$B$2:$B$1602,$A11,'Source Data'!$C$2:$C$1602,"<>")=0,"",AVERAGEIF('Source Data'!$B$2:$B$1602,$A11,'Source Data'!$C$2:$C$1602)) -> 11.25 | D11: =IF(COUNTIFS('Source Data'!$B$2:$B$1602,$A11,'Source Data'!$C$2:$C$1602,"<>")=0,"",_xlfn.MINIFS('Source Data'!$C$2:$C$1602,'Source Data'!$B$2:$B$1602,$A11)) -> 6 | E11: =IF(COUNTIFS('Source Data'!$B$2:$B$1602,$A11,'Source Data'!$C$2:$C$1602,"<>")=0,"",_xlfn.MAXIFS('Source Data'!$C$2:$C$1602,'Source Data'!$B$2:$B$1602,$A11)) -> 24 | F11: =IF(COUNTIFS('Source Data'!$B$2:$B$1602,$A11,'Source Data'!$D$2:$D$1602,"<>")=0,"",AVERAGEIF('Source Data'!$B$2:$B$1602,$A11,'Source Data'!$D$2:$D$1602)) -> 4.75 | G11: =IF(COUNTIFS('Source Data'!$B$2:$B$1602,$A11,'Source Data'!$D$2:$D$1602,"<>")=0,"",_xlfn.MINIFS('Source Data'!$D$2:$D$1602,'Source Data'!$B$2:$B$1602,$A11)) -> 0 | H11: =IF(COUNTIFS('Source Data'!$B$2:$B$1602,$A11,'Source Data'!$D$2:$D$1602,"<>")=0,"",_xlfn.MAXIFS('Source Data'!$D$2:$D$1602,'Source Data'!$B$2:$B$1602,$A11)) -> 14 | I11: =IF(COUNTIFS('Source Data'!$B$2:$B$1602,$A11,'Source Data'!$E$2:$E$1602,"<>")=0,"",AVERAGEIF('Source Data'!$B$2:$B$1602,$A11,'Source Data'!$E$2:$E$1602)) -> 6.5 | J11: =IF(COUNTIFS('Source Data'!$B$2:$B$1602,$A11,'Source Data'!$E$2:$E$1602,"<>")=0,"",_xlfn.MINIFS('Source Data'!$E$2:$E$1602,'Source Data'!$B$2:$B$1602,$A11)) -> 0 | K11: =IF(COUNTIFS('Source Data'!$B$2:$B$1602,$A11,'Source Data'!$E$2:$E$1602,"<>")=0,"",_xlfn.MAXIFS('Source Data'!$E$2:$E$1602,'Source Data'!$B$2:$B$1602,$A11)) -> 12 | L11: =IF(COUNTIFS('Source Data'!$B$2:$B$1602,$A11,'Source Data'!$F$2:$F$1602,"<>")=0,"",AVERAGEIF('Source Data'!$B$2:$B$1602,$A11,'Source Data'!$F$2:$F$1602)) | M11: =IF(COUNTIFS('Source Data'!$B$2:$B$1602,$A11,'Source Data'!$F$2:$F$1602,"<>")=0,"",_xlfn.MINIFS('Source Data'!$F$2:$F$1602,'Source Data'!$B$2:$B$1602,$A11)) | N11: =IF(COUNTIFS('Source Data'!$B$2:$B$1602,$A11,'Source Data'!$F$2:$F$1602,"<>")=0,"",_xlfn.MAXIFS('Source Data'!$F$2:$F$1602,'Source Data'!$B$2:$B$1602,$A11))
A12: Automotive: Parts | B12: =COUNTIF('Source Data'!$B$2:$B$1602,$A12) -> 1 | C12: =IF(COUNTIFS('Source Data'!$B$2:$B$1602,$A12,'Source Data'!$C$2:$C$1602,"<>")=0,"",AVERAGEIF('Source Data'!$B$2:$B$1602,$A12,'Source Data'!$C$2:$C$1602)) -> 8 | D12: =IF(COUNTIFS('Source Data'!$B$2:$B$1602,$A12,'Source Data'!$C$2:$C$1602,"<>")=0,"",_xlfn.MINIFS('Source Data'!$C$2:$C$1602,'Source Data'!$B$2:$B$1602,$A12)) -> 8 | E12: =IF(COUNTIFS('Source Data'!$B$2:$B$1602,$A12,'Source Data'!$C$2:$C$1602,"<>")=0,"",_xlfn.MAXIFS('Source Data'!$C$2:$C$1602,'Source Data'!$B$2:$B$1602,$A12)) -> 8 | F12: =IF(COUNTIFS('Source Data'!$B$2:$B$1602,$A12,'Source Data'!$D$2:$D$1602,"<>")=0,"",AVERAGEIF('Source Data'!$B$2:$B$1602,$A12,'Source Data'!$D$2:$D$1602)) -> 4 | G12: =IF(COUNTIFS('Source Data'!$B$2:$B$1602,$A12,'Source Data'!$D$2:$D$1602,"<>")=0,"",_xlfn.MINIFS('Source Data'!$D$2:$D$1602,'Source Data'!$B$2:$B$1602,$A12)) -> 4 | H12: =IF(COUNTIFS('Source Data'!$B$2:$B$1602,$A12,'Source Data'!$D$2:$D$1602,"<>")=0,"",_xlfn.MAXIFS('Source Data'!$D$2:$D$1602,'Source Data'!$B$2:$B$1602,$A12)) -> 4 | I12: =IF(COUNTIFS('Source Data'!$B$2:$B$1602,$A12,'Source Data'!$E$2:$E$1602,"<>")=0,"",AVERAGEIF('Source Data'!$B$2:$B$1602,$A12,'Source Data'!$E$2:$E$1602)) | J12: =IF(COUNTIFS('Source Data'!$B$2:$B$1602,$A12,'Source Data'!$E$2:$E$1602,"<>")=0,"",_xlfn.MINIFS('Source Data'!$E$2:$E$1602,'Source Data'!$B$2:$B$1602,$A12)) | K12: =IF(COUNTIFS('Source Data'!$B$2:$B$1602,$A12,'Source Data'!$E$2:$E$1602,"<>")=0,"",_xlfn.MAXIFS('Source Data'!$E$2:$E$1602,'Source Data'!$B$2:$B$1602,$A12)) | L12: =IF(COUNTIFS('Source Data'!$B$2:$B$1602,$A12,'Source Data'!$F$2:$F$1602,"<>")=0,"",AVERAGEIF('Source Data'!$B$2:$B$1602,$A12,'Source Data'!$F$2:$F$1602)) | M12: =IF(COUNTIFS('Source Data'!$B$2:$B$1602,$A12,'Source Data'!$F$2:$F$1602,"<>")=0,"",_xlfn.MINIFS('Source Data'!$F$2:$F$1602,'Source Data'!$B$2:$B$1602,$A12)) | N12: =IF(COUNTIFS('Source Data'!$B$2:$B$1602,$A12,'Source Data'!$F$2:$F$1602,"<>")=0,"",_xlfn.MAXIFS('Source Data'!$F$2:$F$1602,'Source Data'!$B$2:$B$1602,$A12))
A13: Automotive: Parts Manufacturing | B13: =COUNTIF('Source Data'!$B$2:$B$1602,$A13) -> 6 | C13: =IF(COUNTIFS('Source Data'!$B$2:$B$1602,$A13,'Source Data'!$C$2:$C$1602,"<>")=0,"",AVERAGEIF('Source Data'!$B$2:$B$1602,$A13,'Source Data'!$C$2:$C$1602)) -> 6 | D13: =IF(COUNTIFS('Source Data'!$B$2:$B$1602,$A13,'Source Data'!$C$2:$C$1602,"<>")=0,"",_xlfn.MINIFS('Source Data'!$C$2:$C$1602,'Source Data'!$B$2:$B$1602,$A13)) -> 0 | E13: =IF(COUNTIFS('Source Data'!$B$2:$B$1602,$A13,'Source Data'!$C$2:$C$1602,"<>")=0,"",_xlfn.MAXIFS('Source Data'!$C$2:$C$1602,'Source Data'!$B$2:$B$1602,$A13)) -> 12 | F13: =IF(COUNTIFS('Source Data'!$B$2:$B$1602,$A13,'Source Data'!$D$2:$D$1602,"<>")=0,"",AVERAGEIF('Source Data'!$B$2:$B$1602,$A13,'Source Data'!$D$2:$D$1602)) -> 3.6666667 | G13: =IF(COUNTIFS('Source Data'!$B$2:$B$1602,$A13,'Source Data'!$D$2:$D$1602,"<>")=0,"",_xlfn.MINIFS('Source Data'!$D$2:$D$1602,'Source Data'!$B$2:$B$1602,$A13)) -> 0 | H13: =IF(COUNTIFS('Source Data'!$B$2:$B$1602,$A13,'Source Data'!$D$2:$D$1602,"<>")=0,"",_xlfn.MAXIFS('Source Data'!$D$2:$D$1602,'Source Data'!$B$2:$B$1602,$A13)) -> 12 | I13: =IF(COUNTIFS('Source Data'!$B$2:$B$1602,$A13,'Source Data'!$E$2:$E$1602,"<>")=0,"",AVERAGEIF('Source Data'!$B$2:$B$1602,$A13,'Source Data'!$E$2:$E$1602)) -> 0 | J13: =IF(COUNTIFS('Source Data'!$B$2:$B$1602,$A13,'Source Data'!$E$2:$E$1602,"<>")=0,"",_xlfn.MINIFS('Source Data'!$E$2:$E$1602,'Source Data'!$B$2:$B$1602,$A13)) -> 0 | K13: =IF(COUNTIFS('Source Data'!$B$2:$B$1602,$A13,'Source Data'!$E$2:$E$1602,"<>")=0,"",_xlfn.MAXIFS('Source Data'!$E$2:$E$1602,'Source Data'!$B$2:$B$1602,$A13)) -> 0 | L13: =IF(COUNTIFS('Source Data'!$B$2:$B$1602,$A13,'Source Data'!$F$2:$F$1602,"<>")=0,"",AVERAGEIF('Source Data'!$B$2:$B$1602,$A13,'Source Data'!$F$2:$F$1602)) | M13: =IF(COUNTIFS('Source Data'!$B$2:$B$1602,$A13,'Source Data'!$F$2:$F$1602,"<>")=0,"",_xlfn.MINIFS('Source Data'!$F$2:$F$1602,'Source Data'!$B$2:$B$1602,$A13)) | N13: =IF(COUNTIFS('Source Data'!$B$2:$B$1602,$A13,'Source Data'!$F$2:$F$1602,"<>")=0,"",_xlfn.MAXIFS('Source Data'!$F$2:$F$1602,'Source Data'!$B$2:$B$1602,$A13))
A14: Automotive: Products & Services | B14: =COUNTIF('Source Data'!$B$2:$B$1602,$A14) -> 1 | C14: =IF(COUNTIFS('Source Data'!$B$2:$B$1602,$A14,'Source Data'!$C$2:$C$1602,"<>")=0,"",AVERAGEIF('Source Data'!$B$2:$B$1602,$A14,'Source Data'!$C$2:$C$1602)) -> 4 | D14: =IF(COUNTIFS('Source Data'!$B$2:$B$1602,$A14,'Source Data'!$C$2:$C$1602,"<>")=0,"",_xlfn.MINIFS('Source Data'!$C$2:$C$1602,'Source Data'!$B$2:$B$1602,$A14)) -> 4 | E14: =IF(COUNTIFS('Source Data'!$B$2:$B$1602,$A14,'Source Data'!$C$2:$C$1602,"<>")=0,"",_xlfn.MAXIFS('Source Data'!$C$2:$C$1602,'Source Data'!$B$2:$B$1602,$A14)) -> 4 | F14: =IF(COUNTIFS('Source Data'!$B$2:$B$1602,$A14,'Source Data'!$D$2:$D$1602,"<>")=0,"",AVERAGEIF('Source Data'!$B$2:$B$1602,$A14,'Source Data'!$D$2:$D$1602)) -> 0 | G14: =IF(COUNTIFS('Source Data'!$B$2:$B$1602,$A14,'Source Data'!$D$2:$D$1602,"<>")=0,"",_xlfn.MINIFS('Source Data'!$D$2:$D$1602,'Source Data'!$B$2:$B$1602,$A14)) -> 0 | H14: =IF(COUNTIFS('Source Data'!$B$2:$B$1602,$A14,'Source Data'!$D$2:$D$1602,"<>")=0,"",_xlfn.MAXIFS('Source Data'!$D$2:$D$1602,'Source Data'!$B$2:$B$1602,$A14)) -> 0 | I14: =IF(COUNTIFS('Source Data'!$B$2:$B$1602,$A14,'Source Data'!$E$2:$E$1602,"<>")=0,"",AVERAGEIF('Source Data'!$B$2:$B$1602,$A14,'Source Data'!$E$2:$E$1602)) | J14: =IF(COUNTIFS('Source Data'!$B$2:$B$1602,$A14,'Source Data'!$E$2:$E$1602,"<>")=0,"",_xlfn.MINIFS('Source Data'!$E$2:$E$1602,'Source Data'!$B$2:$B$1602,$A14)) | K14: =IF(COUNTIFS('Source Data'!$B$2:$B$1602,$A14,'Source Data'!$E$2:$E$1602,"<>")=0,"",_xlfn.MAXIFS('Source Data'!$E$2:$E$1602,'Source Data'!$B$2:$B$1602,$A14)) | L14: =IF(COUNTIFS('Source Data'!$B$2:$B$1602,$A14,'Source Data'!$F$2:$F$1602,"<>")=0,"",AVERAGEIF('Source Data'!$B$2:$B$1602,$A14,'Source Data'!$F$2:$F$1602)) | M14: =IF(COUNTIFS('Source Data'!$B$2:$B$1602,$A14,'Source Data'!$F$2:$F$1602,"<>")=0,"",_xlfn.MINIFS('Source Data'!$F$2:$F$1602,'Source Data'!$B$2:$B$1602,$A14)) | N14: =IF(COUNTIFS('Source Data'!$B$2:$B$1602,$A14,'Source Data'!$F$2:$F$1602,"<>")=0,"",_xlfn.MAXIFS('Source Data'!$F$2:$F$1602,'Source Data'!$B$2:$B$1602,$A14))
A15: Business Services: Food & Hospitality | B15: =COUNTIF('Source Data'!$B$2:$B$1602,$A15) -> 3 | C15: =IF(COUNTIFS('Source Data'!$B$2:$B$1602,$A15,'Source Data'!$C$2:$C$1602,"<>")=0,"",AVERAGEIF('Source Data'!$B$2:$B$1602,$A15,'Source Data'!$C$2:$C$1602)) -> 4.6666667 | D15: =IF(COUNTIFS('Source Data'!$B$2:$B$1602,$A15,'Source Data'!$C$2:$C$1602,"<>")=0,"",_xlfn.MINIFS('Source Data'!$C$2:$C$1602,'Source Data'!$B$2:$B$1602,$A15)) -> 0 | E15: =IF(COUNTIFS('Source Data'!$B$2:$B$1602,$A15,'Source Data'!$C$2:$C$1602,"<>")=0,"",_xlfn.MAXIFS('Source Data'!$C$2:$C$1602,'Source Data'!$B$2:$B$1602,$A15)) -> 12 | F15: =IF(COUNTIFS('Source Data'!$B$2:$B$1602,$A15,'Source Data'!$D$2:$D$1602,"<>")=0,"",AVERAGEIF('Source Data'!$B$2:$B$1602,$A15,'Source Data'!$D$2:$D$1602)) -> 11 | G15: =IF(COUNTIFS('Source Data'!$B$2:$B$1602,$A15,'Source Data'!$D$2:$D$1602,"<>")=0,"",_xlfn.MINIFS('Source Data'!$D$2:$D$1602,'Source Data'!$B$2:$B$1602,$A15)) -> 10 | H15: =IF(COUNTIFS('Source Data'!$B$2:$B$1602,$A15,'Source Data'!$D$2:$D$1602,"<>")=0,"",_xlfn.MAXIFS('Source Data'!$D$2:$D$1602,'Source Data'!$B$2:$B$1602,$A15)) -> 12 | I15: =IF(COUNTIFS('Source Data'!$B$2:$B$1602,$A15,'Source Data'!$E$2:$E$1602,"<>")=0,"",AVERAGEIF('Source Data'!$B$2:$B$1602,$A15,'Source Data'!$E$2:$E$1602)) | J15: =IF(COUNTIFS('Source Data'!$B$2:$B$1602,$A15,'Source Data'!$E$2:$E$1602,"<>")=0,"",_xlfn.MINIFS('Source Data'!$E$2:$E$1602,'Source Data'!$B$2:$B$1602,$A15)) | K15: =IF(COUNTIFS('Source Data'!$B$2:$B$1602,$A15,'Source Data'!$E$2:$E$1602,"<>")=0,"",_xlfn.MAXIFS('Source Data'!$E$2:$E$1602,'Source Data'!$B$2:$B$1602,$A15)) | L15: =IF(COUNTIFS('Source Data'!$B$2:$B$1602,$A15,'Source Data'!$F$2:$F$1602,"<>")=0,"",AVERAGEIF('Source Data'!$B$2:$B$1602,$A15,'Source Data'!$F$2:$F$1602)) | M15: =IF(COUNTIFS('Source Data'!$B$2:$B$1602,$A15,'Source Data'!$F$2:$F$1602,"<>")=0,"",_xlfn.MINIFS('Source Data'!$F$2:$F$1602,'Source Data'!$B$2:$B$1602,$A15)) | N15: =IF(COUNTIFS('Source Data'!$B$2:$B$1602,$A15,'Source Data'!$F$2:$F$1602,"<>")=0,"",_xlfn.MAXIFS('Source Data'!$F$2:$F$1602,'Source Data'!$B$2:$B$1602,$A15))
A16: Business Services: Human Resources | B16: =COUNTIF('Source Data'!$B$2:$B$1602,$A16) -> 5 | C16: =IF(COUNTIFS('Source Data'!$B$2:$B$1602,$A16,'Source Data'!$C$2:$C$1602,"<>")=0,"",AVERAGEIF('Source Data'!$B$2:$B$1602,$A16,'Source Data'!$C$2:$C$1602)) -> 19.9 | D16: =IF(COUNTIFS('Source Data'!$B$2:$B$1602,$A16,'Source Data'!$C$2:$C$1602,"<>")=0,"",_xlfn.MINIFS('Source Data'!$C$2:$C$1602,'Source Data'!$B$2:$B$1602,$A16)) -> 6 | E16: =IF(COUNTIFS('Source Data'!$B$2:$B$1602,$A16,'Source Data'!$C$2:$C$1602,"<>")=0,"",_xlfn.MAXIFS('Source Data'!$C$2:$C$1602,'Source Data'!$B$2:$B$1602,$A16)) -> 36 | F16: =IF(COUNTIFS('Source Data'!$B$2:$B$1602,$A16,'Source Data'!$D$2:$D$1602,"<>")=0,"",AVERAGEIF('Source Data'!$B$2:$B$1602,$A16,'Source Data'!$D$2:$D$1602)) -> 9.4 | G16: =IF(COUNTIFS('Source Data'!$B$2:$B$1602,$A16,'Source Data'!$D$2:$D$1602,"<>")=0,"",_xlfn.MINIFS('Source Data'!$D$2:$D$1602,'Source Data'!$B$2:$B$1602,$A16)) -> 0 | H16: =IF(COUNTIFS('Source Data'!$B$2:$B$1602,$A16,'Source Data'!$D$2:$D$1602,"<>")=0,"",_xlfn.MAXIFS('Source Data'!$D$2:$D$1602,'Source Data'!$B$2:$B$1602,$A16)) -> 25 | I16: =IF(COUNTIFS('Source Data'!$B$2:$B$1602,$A16,'Source Data'!$E$2:$E$1602,"<>")=0,"",AVERAGEIF('Source Data'!$B$2:$B$1602,$A16,'Source Data'!$E$2:$E$1602)) -> 16 | J16: =IF(COUNTIFS('Source Data'!$B$2:$B$1602,$A16,'Source Data'!$E$2:$E$1602,"<>")=0,"",_xlfn.MINIFS('Source Data'!$E$2:$E$1602,'Source Data'!$B$2:$B$1602,$A16)) -> 16 | K16: =IF(COUNTIFS('Source Data'!$B$2:$B$1602,$A16,'Source Data'!$E$2:$E$1602,"<>")=0,"",_xlfn.MAXIFS('Source Data'!$E$2:$E$1602,'Source Data'!$B$2:$B$1602,$A16)) -> 16 | L16: =IF(COUNTIFS('Source Data'!$B$2:$B$1602,$A16,'Source Data'!$F$2:$F$1602,"<>")=0,"",AVERAGEIF('Source Data'!$B$2:$B$1602,$A16,'Source Data'!$F$2:$F$1602)) | M16: =IF(COUNTIFS('Source Data'!$B$2:$B$1602,$A16,'Source Data'!$F$2:$F$1602,"<>")=0,"",_xlfn.MINIFS('Source Data'!$F$2:$F$1602,'Source Data'!$B$2:$B$1602,$A16)) | N16: =IF(COUNTIFS('Source Data'!$B$2:$B$1602,$A16,'Source Data'!$F$2:$F$1602,"<>")=0,"",_xlfn.MAXIFS('Source Data'!$F$2:$F$1602,'Source Data'!$B$2:$B$1602,$A16))
... A190: Wholesale | B190: =COUNTIF('Source Data'!$B$2:$B$1602,$A190) -> 9 | C190: =IF(COUNTIFS('Source Data'!$B$2:$B$1602,$A190,'Source Data'!$C$2:$C$1602,"<>")=0,"",AVERAGEIF('Source Data'!$B$2:$B$1602,$A190,'Source Data'!$C$2:$C$1602)) -> 6.4444444 | D190: =IF(COUNTIFS('Source Data'!$B$2:$B$1602,$A190,'Source Data'!$C$2:$C$1602,"<>")=0,"",_xlfn.MINIFS('Source Data'!$C$2:$C$1602,'Source Data'!$B$2:$B$1602,$A190)) -> 0 | E190: =IF(COUNTIFS('Source Data'!$B$2:$B$1602,$A190,'Source Data'!$C$2:$C$1602,"<>")=0,"",_xlfn.MAXIFS('Source Data'!$C$2:$C$1602,'Source Data'!$B$2:$B$1602,$A190)) -> 14 | F190: =IF(COUNTIFS('Source Data'!$B$2:$B$1602,$A190,'Source Data'!$D$2:$D$1602,"<>")=0,"",AVERAGEIF('Source Data'!$B$2:$B$1602,$A190,'Source Data'!$D$2:$D$1602)) -> 6.8571429 | G190: =IF(COUNTIFS('Source Data'!$B$2:$B$1602,$A190,'Source Data'!$D$2:$D$1602,"<>")=0,"",_xlfn.MINIFS('Source Data'!$D$2:$D$1602,'Source Data'!$B$2:$B$1602,$A190)) -> 0 | H190: =IF(COUNTIFS('Source Data'!$B$2:$B$1602,$A190,'Source Data'!$D$2:$D$1602,"<>")=0,"",_xlfn.MAXIFS('Source Data'!$D$2:$D$1602,'Source Data'!$B$2:$B$1602,$A190)) -> 12 | I190: =IF(COUNTIFS('Source Data'!$B$2:$B$1602,$A190,'Source Data'!$E$2:$E$1602,"<>")=0,"",AVERAGEIF('Source Data'!$B$2:$B$1602,$A190,'Source Data'!$E$2:$E$1602)) -> 1 | J190: =IF(COUNTIFS('Source Data'!$B$2:$B$1602,$A190,'Source Data'!$E$2:$E$1602,"<>")=0,"",_xlfn.MINIFS('Source Data'!$E$2:$E$1602,'Source Data'!$B$2:$B$1602,$A190)) -> 0 | K190: =IF(COUNTIFS('Source Data'!$B$2:$B$1602,$A190,'Source Data'!$E$2:$E$1602,"<>")=0,"",_xlfn.MAXIFS('Source Data'!$E$2:$E$1602,'Source Data'!$B$2:$B$1602,$A190)) -> 2 | L190: =IF(COUNTIFS('Source Data'!$B$2:$B$1602,$A190,'Source Data'!$F$2:$F$1602,"<>")=0,"",AVERAGEIF('Source Data'!$B$2:$B$1602,$A190,'Source Data'!$F$2:$F$1602)) | M190: =IF(COUNTIFS('Source Data'!$B$2:$B$1602,$A190,'Source Data'!$F$2:$F$1602,"<>")=0,"",_xlfn.MINIFS('Source Data'!$F$2:$F$1602,'Source Data'!$B$2:$B$1602,$A190)) | N190: =IF(COUNTIFS('Source Data'!$B$2:$B$1602,$A190,'Source Data'!$F$2:$F$1602,"<>")=0,"",_xlfn.MAXIFS('Source Data'!$F$2:$F$1602,'Source Data'!$B$2:$B$1602,$A190))

Sheet Leave Gap Analysis
A1: Leave Gap Analysis — Paid Maternity vs Paid Paternity Leave by Company
A2: Gap (weeks) = Paid Maternity Leave − Paid Paternity Leave, pulled live from 'Source Data'. A blank paid-leave figure is treated as 0 weeks here so every company gets a gap value (see assumptions in the Summary sheet).
A4: Company | B4: Industry | C4: Paid Maternity Leave (weeks) | D4: Paid Paternity Leave (weeks) | E4: Gap (Maternity − Paternity) | F4: Maternity Advantage?
A5: ='Source Data'!A2 -> Epsilon | B5: ='Source Data'!B2 -> Advertising | C5: ='Source Data'!C2 -> 6 | D5: ='Source Data'!E2 -> 6 | E5: =IFERROR(N(C5)-N(D5),"") -> 0 | F5: =IF(E5>0,"Yes",IF(E5<0,"No (Paternity higher)","Equal")) -> Equal
A6: ='Source Data'!A3 -> The Walt Disney Company | B6: ='Source Data'!B3 -> Arts & Entertainment | C6: ='Source Data'!C3 -> 5 | D6: ='Source Data'!E3 -> 4.5 | E6: =IFERROR(N(C6)-N(D6),"") -> 0.5 | F6: =IF(E6>0,"Yes",IF(E6<0,"No (Paternity higher)","Equal")) -> Yes
A7: ='Source Data'!A4 -> Guild Education | B7: ='Source Data'!B4 -> Business Services: Other | C7: ='Source Data'!C4 -> 14 | D7: ='Source Data'!E4 -> 8 | E7: =IFERROR(N(C7)-N(D7),"") -> 6 | F7: =IF(E7>0,"Yes",IF(E7<0,"No (Paternity higher)","Equal")) -> Yes
A8: ='Source Data'!A5 -> WeWork | B8: ='Source Data'!B5 -> Business Services: Other | C8: ='Source Data'!C5 -> 14 | D8: ='Source Data'!E5 -> 16 | E8: =IFERROR(N(C8)-N(D8),"") -> -2 | F8: =IF(E8>0,"Yes",IF(E8<0,"No (Paternity higher)","Equal")) -> No (Paternity higher)
A9: ='Source Data'!A6 -> Randstad USA | B9: ='Source Data'!B6 -> Business Services: Staffing & Outsourcing | C9: ='Source Data'!C6 -> 5 | D9: ='Source Data'!E6 -> 0 | E9: =IFERROR(N(C9)-N(D9),"") -> 5 | F9: =IF(E9>0,"Yes",IF(E9<0,"No (Paternity higher)","Equal")) -> Yes
A10: ='Source Data'!A7 -> Bain & Company | B10: ='Source Data'!B7 -> Consulting Services | C10: ='Source Data'!C7 -> 20.5 | D10: ='Source Data'!E7 -> 21 | E10: =IFERROR(N(C10)-N(D10),"") -> -0.5 | F10: =IF(E10>0,"Yes",IF(E10<0,"No (Paternity higher)","Equal")) -> No (Paternity higher)
A11: ='Source Data'!A8 -> World 50 | B11: ='Source Data'!B8 -> Consulting Services | C11: ='Source Data'!C8 -> 8 | D11: ='Source Data'!E8 -> 1 | E11: =IFERROR(N(C11)-N(D11),"") -> 7 | F11: =IF(E11>0,"Yes",IF(E11<0,"No (Paternity higher)","Equal")) -> Yes
A12: ='Source Data'!A9 -> ConAgra Foods, Inc. | B12: ='Source Data'!B9 -> Consumer Packaged Goods: Packaged Foods | C12: ='Source Data'!C9 -> 6 | D12: ='Source Data'!E9 -> 2 | E12: =IFERROR(N(C12)-N(D12),"") -> 4 | F12: =IF(E12>0,"Yes",IF(E12<0,"No (Paternity higher)","Equal")) -> Yes
A13: ='Source Data'!A10 -> Anduril Industries | B13: ='Source Data'!B10 -> Defense & Space | C13: ='Source Data'!C10 -> 16 | D13: ='Source Data'!E10 -> 16 | E13: =IFERROR(N(C13)-N(D13),"") -> 0 | F13: =IF(E13>0,"Yes",IF(E13<0,"No (Paternity higher)","Equal")) -> Equal
A14: ='Source Data'!A11 -> Northrop Grumman | B14: ='Source Data'!B11 -> Defense & Space | C14: ='Source Data'!C11 -> 3 | D14: ='Source Data'!E11 -> 2 | E14: =IFERROR(N(C14)-N(D14),"") -> 1 | F14: =IF(E14>0,"Yes",IF(E14<0,"No (Paternity higher)","Equal")) -> Yes
A15: ='Source Data'!A12 -> The University of Vermont | B15: ='Source Data'!B12 -> Educational Services: College & Universities | C15: ='Source Data'!C12 -> 0 | D15: ='Source Data'!E12 -> 0 | E15: =IFERROR(N(C15)-N(D15),"") -> 0 | F15: =IF(E15>0,"Yes",IF(E15<0,"No (Paternity higher)","Equal")) -> Equal
A16: ='Source Data'!A13 -> Belden | B16: ='Source Data'!B13 -> Electronics: Manufacturing | C16: ='Source Data'!C13 -> 0 | D16: ='Source Data'!E13 -> 0 | E16: =IFERROR(N(C16)-N(D16),"") -> 0 | F16: =IF(E16>0,"Yes",IF(E16<0,"No (Paternity higher)","Equal")) -> Equal
... A1605: ='Source Data'!A1602 -> Merrimac Industrial Sales | B1605: ='Source Data'!B1602 -> Wholesale | C1605: ='Source Data'!C1602 -> 0 | D1605: ='Source Data'!E1602 -> 0 | E1605: =IFERROR(N(C1605)-N(D1605),"") -> 0 | F1605: =IF(E1605>0,"Yes",IF(E1605<0,"No (Paternity higher)","Equal")) -> Equal
